ehpp/__init__.py
ehpp/__main__.py
ehpp/consts.py
ehpp/utils.py
ehpp/yaml_utils.py
ehpp-0.1.dist-info/LICENSE
ehpp-0.1.dist-info/METADATA
ehpp-0.1.dist-info/WHEEL
ehpp-0.1.dist-info/entry_points.txt
ehpp-0.1.dist-info/top_level.txt
ehpp-0.1.dist-info/RECORD
